odoo/addons/stock_warehouse_calendar_orderpoint/README.rst
odoo/addons/stock_warehouse_calendar_orderpoint/__init__.py
odoo/addons/stock_warehouse_calendar_orderpoint/__manifest__.py
odoo/addons/stock_warehouse_calendar_orderpoint/i18n/stock_warehouse_calendar_orderpoint.pot
odoo/addons/stock_warehouse_calendar_orderpoint/migrations/14.0.1.1.0/post-mig.py
odoo/addons/stock_warehouse_calendar_orderpoint/migrations/14.0.1.1.0/pre-mig.py
odoo/addons/stock_warehouse_calendar_orderpoint/models/__init__.py
odoo/addons/stock_warehouse_calendar_orderpoint/models/res_company.py
odoo/addons/stock_warehouse_calendar_orderpoint/models/res_config_settings.py
odoo/addons/stock_warehouse_calendar_orderpoint/models/stock_rule.py
odoo/addons/stock_warehouse_calendar_orderpoint/models/stock_warehouse.py
odoo/addons/stock_warehouse_calendar_orderpoint/models/stock_warehouse_orderpoint.py
odoo/addons/stock_warehouse_calendar_orderpoint/readme/CONFIGURE.rst
odoo/addons/stock_warehouse_calendar_orderpoint/readme/CONTRIBUTORS.rst
odoo/addons/stock_warehouse_calendar_orderpoint/readme/DESCRIPTION.rst
odoo/addons/stock_warehouse_calendar_orderpoint/readme/USAGE.rst
odoo/addons/stock_warehouse_calendar_orderpoint/static/description/icon.png
odoo/addons/stock_warehouse_calendar_orderpoint/static/description/index.html
odoo/addons/stock_warehouse_calendar_orderpoint/tests/__init__.py
odoo/addons/stock_warehouse_calendar_orderpoint/tests/common.py
odoo/addons/stock_warehouse_calendar_orderpoint/tests/test_orderpoint_json_lead_days_popover.py
odoo/addons/stock_warehouse_calendar_orderpoint/tests/test_orderpoint_lead_days_date.py
odoo/addons/stock_warehouse_calendar_orderpoint/views/res_config_settings.xml
odoo/addons/stock_warehouse_calendar_orderpoint/views/stock_warehouse.xml
odoo/addons/stock_warehouse_calendar_orderpoint/views/stock_warehouse_orderpoint.xml
odoo14_addon_stock_warehouse_calendar_orderpoint-14.0.1.1.1.dev3.dist-info/METADATA
odoo14_addon_stock_warehouse_calendar_orderpoint-14.0.1.1.1.dev3.dist-info/WHEEL
odoo14_addon_stock_warehouse_calendar_orderpoint-14.0.1.1.1.dev3.dist-info/top_level.txt
odoo14_addon_stock_warehouse_calendar_orderpoint-14.0.1.1.1.dev3.dist-info/RECORD
