Metadata-Version: 2.1
Name: odoo14-addon-stock_warehouse_calendar_orderpoint
Version: 14.0.1.1.1.dev3
Summary: Adds a calendar to the Warehouse for reordering rules
Home-page: https://github.com/OCA/stock-logistics-warehouse
Author: Camptocamp, Odoo Community Association (OCA)
Author-email: support@odoo-community.org
License: LGPL-3
Classifier: Programming Language :: Python
Classifier: Framework :: Odoo
Classifier: Framework :: Odoo :: 14.0
Classifier: License :: OSI Approved :: GNU Lesser General Public License v3 (LGPLv3)
Classifier: Development Status :: 5 - Production/Stable
Requires-Python: >=3.6
Requires-Dist: odoo14-addon-stock-warehouse-calendar
Requires-Dist: odoo<14.1dev,>=14.0a
